llama_index/packs/agents_coa/__init__.py
llama_index/packs/agents_coa/base.py
llama_index/packs/agents_coa/output_parser.py
llama_index/packs/agents_coa/prompts.py
llama_index/packs/agents_coa/step.py
llama_index/packs/agents_coa/utils.py
llama_index_packs_agents_coa-0.3.2.dist-info/METADATA
llama_index_packs_agents_coa-0.3.2.dist-info/WHEEL
llama_index_packs_agents_coa-0.3.2.dist-info/licenses/LICENSE
llama_index_packs_agents_coa-0.3.2.dist-info/RECORD
