Metadata-Version: 2.4
Name: llama-index-packs-agents-coa
Version: 0.3.2
Summary: llama-index packs for chain-of-abstraction
Author-email: Logan Markewich <logan@runllama.ai>
Maintainer: jerryjliu
License-Expression: MIT
License-File: LICENSE
Keywords: abstraction,agent,chain,coa
Requires-Python: <4.0,>=3.9
Requires-Dist: llama-index-core<0.13,>=0.12.0
